ele2364/__init__.py
ele2364/environments.py
ele2364/networks.py
ele2364/flappy_bird_gym/__init__.py
ele2364/flappy_bird_gym/assets/__init__.py
ele2364/flappy_bird_gym/assets/sprites/0.png
ele2364/flappy_bird_gym/assets/sprites/1.png
ele2364/flappy_bird_gym/assets/sprites/2.png
ele2364/flappy_bird_gym/assets/sprites/3.png
ele2364/flappy_bird_gym/assets/sprites/4.png
ele2364/flappy_bird_gym/assets/sprites/5.png
ele2364/flappy_bird_gym/assets/sprites/6.png
ele2364/flappy_bird_gym/assets/sprites/7.png
ele2364/flappy_bird_gym/assets/sprites/8.png
ele2364/flappy_bird_gym/assets/sprites/9.png
ele2364/flappy_bird_gym/assets/sprites/__init__.py
ele2364/flappy_bird_gym/assets/sprites/background-day.png
ele2364/flappy_bird_gym/assets/sprites/background-night.png
ele2364/flappy_bird_gym/assets/sprites/base.png
ele2364/flappy_bird_gym/assets/sprites/bluebird-downflap.png
ele2364/flappy_bird_gym/assets/sprites/bluebird-midflap.png
ele2364/flappy_bird_gym/assets/sprites/bluebird-upflap.png
ele2364/flappy_bird_gym/assets/sprites/gameover.png
ele2364/flappy_bird_gym/assets/sprites/message.png
ele2364/flappy_bird_gym/assets/sprites/pipe-green.png
ele2364/flappy_bird_gym/assets/sprites/pipe-red.png
ele2364/flappy_bird_gym/assets/sprites/redbird-downflap.png
ele2364/flappy_bird_gym/assets/sprites/redbird-midflap.png
ele2364/flappy_bird_gym/assets/sprites/redbird-upflap.png
ele2364/flappy_bird_gym/assets/sprites/yellowbird-downflap.png
ele2364/flappy_bird_gym/assets/sprites/yellowbird-midflap.png
ele2364/flappy_bird_gym/assets/sprites/yellowbird-upflap.png
ele2364/flappy_bird_gym/envs/__init__.py
ele2364/flappy_bird_gym/envs/flappy_bird_env_simple.py
ele2364/flappy_bird_gym/envs/game_logic.py
ele2364/flappy_bird_gym/envs/renderer.py
ele2364/flappy_bird_gym/envs/utils.py
ele2364-0.1.3.dist-info/licenses/LICENSE
ele2364-0.1.3.dist-info/METADATA
ele2364-0.1.3.dist-info/WHEEL
ele2364-0.1.3.dist-info/top_level.txt
ele2364-0.1.3.dist-info/RECORD
