Metadata-Version: 2.4
Name: ele2364
Version: 0.1.3
Summary: ELE2364 (reinforcement learning) support package
Home-page: http://github.com/wcaarls/ele2364
Author: Wouter Caarls
Author-email: wouter@puc-rio.br
License: MIT
Keywords: reinforcement learning
Classifier: Development Status :: 4 - Beta
Classifier: Environment :: Console
Classifier: License :: OSI Approved :: MIT License
Classifier: Programming Language :: Python :: 3
Classifier: Topic :: Education
Classifier: Topic :: Scientific/Engineering :: Artificial Intelligence
License-File: LICENSE
Requires-Dist: numpy
Requires-Dist: gymnasium
Requires-Dist: pygame
Requires-Dist: torch>=2.1.0
Dynamic: author
Dynamic: author-email
Dynamic: classifier
Dynamic: description
Dynamic: description-content-type
Dynamic: home-page
Dynamic: keywords
Dynamic: license
Dynamic: license-file
Dynamic: requires-dist
Dynamic: summary
